smsit_wrapper/__init__.py
smsit_wrapper/main.py
smsit_wrapper-0.0.2.dist-info/LICENSE
smsit_wrapper-0.0.2.dist-info/METADATA
smsit_wrapper-0.0.2.dist-info/WHEEL
smsit_wrapper-0.0.2.dist-info/top_level.txt
smsit_wrapper-0.0.2.dist-info/RECORD
