Metadata-Version: 2.1
Name: smsit-wrapper
Version: 0.0.2
Summary: SMS-iT API Python wrapper 0.0.2
Home-page: UNKNOWN
Author: SMS-iT
Author-email: <opps@smsit.ai>
License: UNKNOWN
Keywords: python,smsit,cloud,decentralized,api,wrapper
Platform: UNKNOWN
Classifier: Development Status :: 1 - Planning
Classifier: Intended Audience :: Developers
Classifier: Programming Language :: Python :: 3
Classifier: Operating System :: Unix
Classifier: Operating System :: MacOS :: MacOS X
Classifier: Operating System :: Microsoft :: Windows
Requires-Dist: requests
Requires-Dist: python-dateutil
